Workbook

Sheet Instructions
B2: THE WEALTH DRAIN — RETIREMENT TOOLKIT
B3: Updated for 2026 Tax Year
B5: WELCOME
B7: HOW TO USE THIS TOOLKIT
B8: This workbook contains 6 tabs. Each one is a standalone tool, but they also work together — your inputs on the Reference Data tab feed into every other sheet automatically.
B10: Step 1: Start with the Reference Data tab
B11: Enter your personal details (age, income, filing status, state). These flow into every calculator in the workbook. The 2026 federal tax brackets and Social Security figures are pre-loaded — you only need to update them once a year (instructions below).
B13: Step 2: Explore each tab
B14: • Retirement Readiness Scorecard — Your overall financial health dashboard. Grades your savings rate, projects your freedom number, and shows where you stand.
B15: • Fee Drain Analyzer — Compare up to 4 funds side-by-side. See exactly how much fees cost you over your investment timeline.
B16: • Roth Conversion Planner — Model year-by-year Roth conversions and see the tax impact of different conversion amounts.
B17: • Social Security Optimizer — Compare claiming at 62, 67, and 70. Find your break-even age and see lifetime benefit projections.
... B43: YouTube: youtube.com/@TheQuietDrain

Sheet Reference Data
B2: REFERENCE DATA & PERSONAL INPUTS
B3: All blue/yellow cells are editable. These values feed every tab in the workbook.
B5: YOUR PERSONAL INFORMATION
B6: Current Age | C6: 30
B7: Retirement Age (Target) | C7: 65
B8: Annual Gross Income ($) | C8: 75000
B9: Filing Status | C9: Single
B10: State | C10: No State Income Tax
B11: Current Retirement Savings ($) | C11: 50000
B12: Monthly Contribution ($) | C12: 1250
B13: Employer Match (%) | C13: 0.03
B14: Expected Annual Return (%) | C14: 0.08
B15: Expected Inflation (%) | C15: 0.03
B16: Annual Expenses in Retirement ($) | C16: 48000
B17: Filing Status options: Single, Married Filing Jointly, Married Filing Separately, Head of Household
B19: 2026 FEDERAL TAX BRACKETS (Single)
B20: Tax Rate | C20: From ($) | D20: To ($) | E20: Notes
B21: 0.1 | C21: 0 | D21: 11925
B22: 0.12 | C22: 11926 | D22: 48475
B23: 0.22 | C23: 48476 | D23: 103350
B24: 0.24 | C24: 103351 | D24: 197300
B25: 0.32 | C25: 197301 | D25: 250525
B26: 0.35 | C26: 250526 | D26: 626350
B27: 0.37 | C27: 626351 | D27: 99999999 | E27: Top bracket
B29: Standard Deduction (2026) | C29: 15700
B31: SOCIAL SECURITY REFERENCE (2026)
B32: Full Retirement Age (FRA) | C32: 67 | E32: Born 1960 or later
B33: Max Monthly Benefit at FRA | C33: 4018 | E33: 2026 figure
B34: Early Claiming Age | C34: 62
B35: Early Claiming Reduction (%) | C35: 0.3 | E35: 30% reduction at 62 if FRA is 67
B36: Delayed Retirement Credits (%/yr) | C36: 0.08 | E36: 8% per year past FRA up to 70
B37: COLA Estimate (%) | C37: 0.025 | E37: Historical average ~2-3%
B38: Earnings Test Limit (under FRA) | C38: 23400 | E38: 2026 limit
B39: First Bend Point ($) | C39: 1226 | E39: 2026 PIA formula
B40: Second Bend Point ($) | C40: 7391 | E40: 2026 PIA formula
B43: LAST UPDATED: January 2026
B44: Next update needed: October/November 2026 (when IRS releases 2027 brackets)

Sheet Readiness Scorecard
B2: RETIREMENT READINESS SCORECARD
B3: Your financial health at a glance. All data pulls from the Reference Data tab.
B5: KEY METRICS
B6: Years to Retirement | C6: ='Reference Data'!C7-'Reference Data'!C6 -> 35
B7: Annual Contribution ($) | C7: ='Reference Data'!C12*12 -> 15000
B8: Employer Match Contribution ($) | C8: ='Reference Data'!C8*'Reference Data'!C13 -> 2250
B9: Total Annual Savings ($) | C9: =C7+C8 -> 17250
B11: SAVINGS RATE GRADE
B12: Savings Rate | C12: =C9/'Reference Data'!C8 -> 0.23 | D12: Grade: | E12: =IF(C12>=0.25,"A — Excellent",IF(C12>=0.2,"B — Great",IF(C12>=0.15,"C — Good",IF(C12>=0.1,"D — Needs Work","F — Critical")))) -> B — Great
B13: Target: 20%+ of gross income for on-track retirement
B15: YOUR FREEDOM NUMBER
B16: Annual Expenses in Retirement | C16: ='Reference Data'!C16 -> 48000
B17: Freedom Number (25x expenses) | C17: =C16*25 -> 1200000 | E17: Based on the 4% rule
B19: Projected Portfolio at Retirement | C19: =FV('Reference Data'!C14,C6,-C9,-'Reference Data'!C11) -> 3711732.1
B20: Gap to Freedom Number | C20: =C19-C17 -> 2511732.1 | D20: Status: | E20: =IF(C20>=0,"ON TRACK","BEHIND — Increase savings or timeline") -> ON TRACK
B22: PASSIVE INCOME PROJECTION
B23: Monthly Freedom Income (4% rule) | C23: =C19*0.04/12 -> 12372.44
B24: Yearly Passive Cashflow | C24: =C19*0.04 -> 148469.28
B25: Covers Monthly Expenses? | C25: =C16/12 -> 4000 | D25: Need/mo | E25: =IF(C23>=C25,"YES — Fully funded","NO — Shortfall of "&TEXT(C25-C23,"$#,##0")&"/mo") -> YES — Fully funded
B27: COMPOUND INTEREST MILESTONES
B28: Years to $100K | C28: =IFERROR(NPER('Reference Data'!C14,-(C9),-('Reference Data'!C11),100000),"Already there!") -> 2.2409944 | E28: The $100K barrier — after this, compounding accelerates
B29: Years to $500K | C29: =IFERROR(NPER('Reference Data'!C14,-(C9),-('Reference Data'!C11),500000),"Already there!") -> 12.877564
B30: Years to $1,000,000 | C30: =IFERROR(NPER('Reference Data'!C14,-(C9),-('Reference Data'!C11),1000000),"Already there!") -> 19.762312
B31: Years to Freedom Number | C31: =IFERROR(NPER('Reference Data'!C14,-(C9),-('Reference Data'!C11),C17),"Already there!") -> 21.741401 | E31: =IF(ISNUMBER(C31),"You'll hit freedom at age "&TEXT('Reference Data'!C6+C31,"0"),"") -> You'll hit freedom at age 52

Sheet Fee Drain Analyzer
B2: FEE DRAIN ANALYZER
B3: See how much fees silently eat from your portfolio. Compare up to 4 funds.
B5: FUND COMPARISON
C6: Fund A | D6: Fund B | E6: Fund C | F6: Fund D
B7: Fund Name | C7: VTI (Total Market) | D7: VFIAX (S&P 500) | E7: Growth Fund X | F7: Managed Fund Y
B8: Expense Ratio (%) | C8: 0.0003 | D8: 0.0004 | E8: 0.0075 | F8: 0.01
B9: Annual Return (%) | C9: 0.08 | D9: 0.08 | E9: 0.08 | F9: 0.08
B10: Initial Investment ($) | C10: 50000
B11: Annual Addition ($) | C11: 15000
B12: Time Horizon (Years) | C12: 30
B14: RESULTS
C15: =B7 -> Fund Name | D15: =B7 -> Fund Name | E15: =B7 -> Fund Name | F15: =B7 -> Fund Name
B16: Final Balance ($) | C16: =FV(C9-C8,$C$12,-$C$11,-$C$10) -> 2188882.6 | D16: =FV(D9-D8,$C$12,-$C$11,-$C$10) -> 2184403 | E16: =FV(E9-E8,$C$12,-$C$11,-$C$10) -> 1890484.3 | F16: =FV(F9-F8,$C$12,-$C$11,-$C$10) -> 1797524.5
B17: Balance Without Fees ($) | C17: =FV(C9,$C$12,-$C$11,-$C$10) -> 2202381 | D17: =FV(D9,$C$12,-$C$11,-$C$10) -> 2202381 | E17: =FV(E9,$C$12,-$C$11,-$C$10) -> 2202381 | F17: =FV(F9,$C$12,-$C$11,-$C$10) -> 2202381
B18: MONEY LOST TO FEES ($) | C18: =C17-C16 -> 13498.446 | D18: =D17-D16 -> 17977.966 | E18: =E17-E16 -> 311896.7 | F18: =F17-F16 -> 404856.46
B19: % of Wealth Lost to Fees | C19: =IFERROR(C18/C17,0) -> 0.0061290238 | D19: =IFERROR(D18/D17,0) -> 0.0081629681 | E19: =IFERROR(E18/E17,0) -> 0.14161796 | F19: =IFERROR(F18/F17,0) -> 0.18382671
B20: Effective Net Return | C20: =C9-C8 -> 0.0797 | D20: =D9-D8 -> 0.0796 | E20: =E9-E8 -> 0.0725 | F20: =F9-F8 -> 0.07
B22: YEAR-BY-YEAR: LOWEST FEE vs HIGHEST FEE
B23: Year | C23: Low-Fee Balance | D23: High-Fee Balance | E23: Cumulative Fee Drain | F23: Fee Drain This Year | G23: Lost as % of Total
B24: 0 | C24: =$C$10 -> 50000 | D24: =$C$10 -> 50000 | E24: =C24-D24 -> 0 | F24: =IF(B24=0,0,E24-E24) -> 0 | G24: =IFERROR(E24/C24,0) -> 0
B25: 1 | C25: =(C24+$C$11)*(1+$C$9-$C$8) -> 70180.5 | D25: =(D24+$C$11)*(1+$F$9-$F$8) -> 69550 | E25: =C25-D25 -> 630.5 | F25: =IF(B25=0,0,E25-E24) -> 630.5 | G25: =IFERROR(E25/C25,0) -> 0.008983977
B26: 2 | C26: =(C25+$C$11)*(1+$C$9-$C$8) -> 91969.386 | D26: =(D25+$C$11)*(1+$F$9-$F$8) -> 90468.5 | E26: =C26-D26 -> 1500.8859 | F26: =IF(B26=0,0,E26-E25) -> 870.38585 | G26: =IFERROR(E26/C26,0) -> 0.016319407
B27: 3 | C27: =(C26+$C$11)*(1+$C$9-$C$8) -> 115494.85 | D27: =(D26+$C$11)*(1+$F$9-$F$8) -> 112851.29 | E27: =C27-D27 -> 2643.5509 | F27: =IF(B27=0,0,E27-E26) -> 1142.6651 | G27: =IFERROR(E27/C27,0) -> 0.022888908
B28: 4 | C28: =(C27+$C$11)*(1+$C$9-$C$8) -> 140895.29 | D28: =(D27+$C$11)*(1+$F$9-$F$8) -> 136800.89 | E28: =C28-D28 -> 4094.3995 | F28: =IF(B28=0,0,E28-E27) -> 1450.8486 | G28: =IFERROR(E28/C28,0) -> 0.029059876
B29: 5 | C29: =(C28+$C$11)*(1+$C$9-$C$8) -> 168320.14 | D29: =(D28+$C$11)*(1+$F$9-$F$8) -> 162426.95 | E29: =C29-D29 -> 5893.1917 | F29: =IF(B29=0,0,E29-E28) -> 1798.7922 | G29: =IFERROR(E29/C29,0) -> 0.035011804
B30: 6 | C30: =(C29+$C$11)*(1+$C$9-$C$8) -> 197930.75 | D30: =(D29+$C$11)*(1+$F$9-$F$8) -> 189846.83 | E30: =C30-D30 -> 8083.9205 | F30: =IF(B30=0,0,E30-E29) -> 2190.7288 | G30: =IFERROR(E30/C30,0) -> 0.040842165
B31: 7 | C31: =(C30+$C$11)*(1+$C$9-$C$8) -> 229901.34 | D31: =(D30+$C$11)*(1+$F$9-$F$8) -> 219186.11 | E31: =C31-D31 -> 10715.223 | F31: =IF(B31=0,0,E31-E30) -> 2631.3028 | G31: =IFERROR(E31/C31,0) -> 0.046607921
B32: 8 | C32: =(C31+$C$11)*(1+$C$9-$C$8) -> 264419.97 | D32: =(D31+$C$11)*(1+$F$9-$F$8) -> 250579.14 | E32: =C32-D32 -> 13840.832 | F32: =IF(B32=0,0,E32-E31) -> 3125.6086 | G32: =IFERROR(E32/C32,0) -> 0.052344124
B33: 9 | C33: =(C32+$C$11)*(1+$C$9-$C$8) -> 301689.74 | D33: =(D32+$C$11)*(1+$F$9-$F$8) -> 284169.68 | E33: =C33-D33 -> 17520.064 | F33: =IF(B33=0,0,E33-E32) -> 3679.232 | G33: =IFERROR(E33/C33,0) -> 0.058073117
B34: 10 | C34: =(C33+$C$11)*(1+$C$9-$C$8) -> 341929.92 | D34: =(D33+$C$11)*(1+$F$9-$F$8) -> 320111.56 | E34: =C34-D34 -> 21818.359 | F34: =IF(B34=0,0,E34-E33) -> 4298.295 | G34: =IFERROR(E34/C34,0) -> 0.063809447
B35: 11 | C35: =(C34+$C$11)*(1+$C$9-$C$8) -> 385377.23 | D35: =(D34+$C$11)*(1+$F$9-$F$8) -> 358569.37 | E35: =C35-D35 -> 26807.864 | F35: =IF(B35=0,0,E35-E34) -> 4989.5053 | G35: =IFERROR(E35/C35,0) -> 0.069562657
B36: 12 | C36: =(C35+$C$11)*(1+$C$9-$C$8) -> 432287.3 | D36: =(D35+$C$11)*(1+$F$9-$F$8) -> 399719.22 | E36: =C36-D36 -> 32568.074 | F36: =IF(B36=0,0,E36-E35) -> 5760.2096 | G36: =IFERROR(E36/C36,0) -> 0.075338956
... B54: 30 | C54: =(C53+$C$11)*(1+$C$9-$C$8) -> 2323569.6 | D54: =(D53+$C$11)*(1+$F$9-$F$8) -> 1896708.4 | E54: =C54-D54 -> 426861.27 | F54: =IF(B54=0,0,E54-E53) -> 47434.752 | G54: =IFERROR(E54/C54,0) -> 0.18370926
